{
  "_readme": "생활밀착 점수 가중치 사전. 값이 높을수록 시청자 생활과 직결. 코드 수정 없이 이 파일만 편집하면 됩니다.",
  "keywords": {
    "給料": 3,
    "賃金": 3,
    "実質賃金": 3,
    "手取り": 3,
    "物価": 3,
    "値上げ": 2,
    "年金": 3,
    "光熱費": 3,
    "電気代": 3,
    "ガソリン": 3,
    "食費": 3,
    "家計": 3,
    "家賃": 2,
    "税金": 2,
    "社会保険料": 3,
    "教育費": 2,
    "生活費": 3,
    "消費税": 2,
    "医療費": 2,
    "食料品": 2,
    "住宅ローン": 3,
    "預金": 2,
    "金利": 2,
    "インフレ": 2,
    "消費者物価": 3,
    "雇用": 2,
    "失業": 2,
    "節約": 2,
    "家庭": 2,
    "生活保護": 3,
    "介護": 2,
    "育児": 2,
    "子育て": 2,
    "奨学金": 3,
    "ふるさと納税": 2,
    "給付金": 3,
    "補助金": 2
  }
}
